REGIR/REGIR.py
REGIR/__init__.py
REGIR-1.0.5.dist-info/LICENSE
REGIR-1.0.5.dist-info/METADATA
REGIR-1.0.5.dist-info/WHEEL
REGIR-1.0.5.dist-info/top_level.txt
REGIR-1.0.5.dist-info/RECORD
