Metadata-Version: 2.1
Name: REGIR
Version: 1.0.5
Summary: An algorithm for non-Markovian stochastic simulation
Home-page: https://github.com/Aurelien-Pelissier/REGIR/
Author: Aurelien Pelissier
Author-email: aurelien.pelissier.38@gmail.com
License: UNKNOWN
Keywords: Gillespie,modeling,stochastic,simulation
Platform: UNKNOWN
Classifier: Programming Language :: Python :: 3
Classifier: License :: OSI Approved :: MIT License
Classifier: Operating System :: OS Independent
License-File: LICENSE
